sequana_pipelines/depletion/__init__.py
sequana_pipelines/depletion/config.yaml
sequana_pipelines/depletion/depletion.rules
sequana_pipelines/depletion/main.py
sequana_pipelines/depletion/schema.yaml
sequana_pipelines/depletion/tools.txt
sequana_depletion-0.3.0.dist-info/LICENSE
sequana_depletion-0.3.0.dist-info/METADATA
sequana_depletion-0.3.0.dist-info/WHEEL
sequana_depletion-0.3.0.dist-info/entry_points.txt
sequana_depletion-0.3.0.dist-info/RECORD
