Metadata-Version: 2.1
Name: sequana-depletion
Version: 0.3.0
Summary: A pipeline to deplete reads from a given reference
Home-page: https://github.com/sequana/depletion
License: BSD-3
Keywords: snakemake,sequana,depletion,NGS
Author: Sequana Team
Requires-Python: >=3.8,<4.0
Classifier: Development Status :: 5 - Production/Stable
Classifier: Intended Audience :: Developers
Classifier: Intended Audience :: Education
Classifier: Intended Audience :: End Users/Desktop
Classifier: Intended Audience :: Science/Research
Classifier: License :: OSI Approved :: BSD License
Classifier: License :: Other/Proprietary License
Classifier: Operating System :: POSIX :: Linux
Classifier: Programming Language :: Python :: 3
Classifier: Programming Language :: Python :: 3.8
Classifier: Programming Language :: Python :: 3.9
Classifier: Programming Language :: Python :: 3.10
Classifier: Programming Language :: Python :: 3.11
Classifier: Programming Language :: Python :: 3.12
Classifier: Topic :: Scientific/Engineering :: Bio-Informatics
Classifier: Topic :: Scientific/Engineering :: Information Analysis
Classifier: Topic :: Software Development :: Libraries :: Python Modules
Requires-Dist: click (>=8.1.7,<9.0.0)
Requires-Dist: click-completion (>=0.5.2,<0.6.0)
Requires-Dist: sequana (>=0.16.4,<0.17.0)
Requires-Dist: sequana-pipetools (>=0.16.6,<0.17.0)
Project-URL: Repository, https://github.com/sequana/depletion
